LICENSE
README.md
setup.py
reip/__init__.py
reip/base.py
reip/block.py
reip/constants.py
reip/exceptions.py
reip/graph.py
reip/helpers.py
reip/interface.py
reip/stream.py
reip/task.py
reip.egg-info/PKG-INFO
reip.egg-info/SOURCES.txt
reip.egg-info/dependency_links.txt
reip.egg-info/requires.txt
reip.egg-info/top_level.txt
reip/blocks/__init__.py
reip/blocks/archive.py
reip/blocks/buffer.py
reip/blocks/diskmonitor.py
reip/blocks/dummy.py
reip/blocks/encrypt.py
reip/blocks/misc.py
reip/blocks/ml.py
reip/blocks/os_watch.py
reip/blocks/output.py
reip/blocks/shell.py
reip/blocks/streamer.py
reip/blocks/sync.py
reip/blocks/upload.py
reip/blocks/audio/__init__.py
reip/blocks/audio/dummy.py
reip/blocks/audio/features.py
reip/blocks/audio/ml.py
reip/blocks/audio/output.py
reip/blocks/audio/plot.py
reip/blocks/audio/source.py
reip/blocks/video/__init__.py
reip/blocks/video/core.py
reip/blocks/video/effects.py
reip/blocks/video/gstreamer.py
reip/blocks/video/models/__init__.py
reip/blocks/video/models/objects.py
reip/blocks/video/models/posenet.py
reip/blocks/video/models/segmentation.py
reip/blocks/video/models/style.py
reip/models/__init__.py
reip/stores/__init__.py
reip/stores/base.py
reip/stores/customer.py
reip/stores/plasma.py
reip/stores/pointers.py
reip/stores/producer.py
reip/stores/queue.py
reip/stores/queue_store.py
reip/stores/store.py
reip/util/__init__.py
reip/util/background_process.py
reip/util/config.py
reip/util/debug.py
reip/util/func.py
reip/util/gstream.py
reip/util/handlers.py
reip/util/iters.py
reip/util/logging.py
reip/util/meta.py
reip/util/misc.py
reip/util/remote.py
reip/util/shell.py
reip/util/statistics.py
reip/util/status.py
reip/util/stopwatch.py
reip/util/test.py
reip/util/text.py
reip/util/wpa_supplicant.py
reip/util/writer.py