Metadata-Version: 2.1
Name: reip
Version: 0.0.1
Summary: UNKNOWN
Home-page: https://github.com/reip-project/reip
Author: Yurii Piadyk, Bea Steers
Author-email: ypiadyk@nyu.edu
License: BSD 3-Clause Clear License
Keywords: iot embedded app pipeline block multiprocessing
Platform: UNKNOWN
Provides-Extra: plasma
Provides-Extra: tflite
Provides-Extra: audio
Provides-Extra: video
Provides-Extra: encrypt
Provides-Extra: vis
Provides-Extra: docs
License-File: LICENSE
